testerun/.gitlab-ci.yml
testerun/__init__.py
testerun/main.py
testerun/.git/FETCH_HEAD
testerun/.git/HEAD
testerun/.git/config
testerun/.git/index
testerun/.git/shallow
testerun/.git/logs/HEAD
testerun/.git/logs/refs/remotes/origin/main
testerun/.git/objects/00/79166bfe9ad9bdf4c98bf768c94a9479ac5b0e
testerun/.git/objects/0a/d5c1d989ab69eec07055759e31a2199c2b3b02
testerun/.git/objects/10/50ba9fd3736d1e8ca801a944470c391d20b47e
testerun/.git/objects/10/c0c52414772b382a7b7647181dd96ea72760c0
testerun/.git/objects/13/9f78f94361253cd7109266ba8b5f52262e8fb8
testerun/.git/objects/15/2c82ff946f30b137abdbc7228f8cc2cccc5c12
testerun/.git/objects/1b/77d8616b7f5562ca21b853e07d44c2b9dd4dc4
testerun/.git/objects/1d/1e85f21cb721fd6ddef074625921f4919ec0a9
testerun/.git/objects/1f/51e1407de06001881f59c4a343ad66f95b5eb1
testerun/.git/objects/2a/2636a5df2bbdbef07b6baa6bf5cce8c9374b6d
testerun/.git/objects/30/18e2a3aa5a4f5bf2a43df0e3fff233d7931f37
testerun/.git/objects/3a/051abd59227329132cb2d18a9d2d9bada173ea
testerun/.git/objects/3a/571b5e11251792937e347844c948338a3f8f3c
testerun/.git/objects/3a/954b8503a46981a506193691ba02d4505d3aa9
testerun/.git/objects/3b/6c26b01ccfc621d469b57dda91c53c4bdde29d
testerun/.git/objects/3d/407d48b6bdf88cf5e80d53cb2e7ebbf3968564
testerun/.git/objects/3d/4d6a5ae91042d26cfdaa3298eafd1ede798b49
testerun/.git/objects/48/b29c59750d76ea306d0c5627e1bf7faffb325f
testerun/.git/objects/4f/4986f6916968f6b33a57ced6443dc1f1014c6c
testerun/.git/objects/50/658f41024a227e796300b59294ae8abfff3071
testerun/.git/objects/50/98215ec38554cf1788b2cca71ef2a42d3b410b
testerun/.git/objects/53/9052496a65d95d0e4bfc15613b756752d66a5a
testerun/.git/objects/55/13402a535f908eda0c1eaf622d2f5d10a6cb15
testerun/.git/objects/5a/cf8bab252a51dfe53cf05e0883bdb052b7c823
testerun/.git/objects/5b/411361b8992411474827a76f6ce0590d80eb8b
testerun/.git/objects/5d/f4a1a7a07a1f9c4616cc340ef61dbb77421e2a
testerun/.git/objects/61/416e53c354036f71ca64752c4fac5a3ae7ff79
testerun-0.0.3.dist-info/LICENSE
testerun-0.0.3.dist-info/METADATA
testerun-0.0.3.dist-info/WHEEL
testerun-0.0.3.dist-info/entry_points.txt
testerun-0.0.3.dist-info/top_level.txt
testerun-0.0.3.dist-info/RECORD
