Metadata-Version: 2.1
Name: testerun
Version: 0.0.3
Summary: Test Description
Home-page: UNKNOWN
Author: Irakli  Gzirishvili
Author-email: gziraklirex@gmail.com
License: UNKNOWN
Platform: UNKNOWN
Classifier: Programming Language :: Python :: 3
Classifier: License :: OSI Approved :: MIT License
Classifier: Operating System :: Microsoft :: Windows
License-File: LICENSE
Requires-Dist: clight
